tcgplayersdk/UnlimitedBaseSet.csv
tcgplayersdk/category_enum.py
tcgplayersdk/decorators.py
tcgplayersdk/exceptions.py
tcgplayersdk/schemas/api_response.py
tcgplayersdk/schemas/category.py
tcgplayersdk/schemas/group.py
tcgplayersdk/schemas/identity.py
tcgplayersdk/schemas/product.py
tcgplayersdk/schemas/product_price.py
tcgplayersdk/schemas/sku_price.py
tcgplayersdk/schemas/snake_case_schema.py
tcgplayersdk/sdk.py
tcgplayersdk/util.py
tcgplayersdk-0.1.2.dist-info/LICENSE
tcgplayersdk-0.1.2.dist-info/WHEEL
tcgplayersdk-0.1.2.dist-info/METADATA
tcgplayersdk-0.1.2.dist-info/RECORD
